{"duration": 3.2070207595825195, "input_args": {"transformer": "Pipeline(steps=[('mc', MisCare(missing_threshold=0.05)), ('cc', ConstantCare()),\n                ('ur', URareCare(threshold=0.025)), ('cc2', ConstantCare()),\n                ('one_hot', CustomOneHotEncoder()),\n                ('feature_selection',\n                 FeatureSelection(alpha=0.1, model_type='reg')),\n                ('collinear_care',\n                 CollinearCare(dist_method='correlation', threshold=0.05))])", "X": "       p1   p2   p3   p4   p5   p6   p7  ... p350 p351 p352 p353 p354 p355 p356\nS2    NaN  NaN  NaN    T    E    G    P  ...  NaN    S    S    V    S    P    A\nS5    NaN  NaN  NaN    T    E    G    P  ...  NaN    S    S    V    S    P    A\nS6      M    N    G    T    E    G    P  ...  NaN    S    S    V    S    P    A\nS9    NaN  NaN  NaN    T    E    G    P  ...  NaN    S    S    V    S    P    A\nS10   NaN  NaN  NaN    T    E    G    P  ...    S    S    S    V    S    P    A\n...   ...  ...  ...  ...  ...  ...  ...  ...  ...  ...  ...  ...  ...  ...  ...\nS836  NaN  NaN  NaN  NaN  NaN    H    E  ...  NaN  NaN  NaN  NaN    A    P    E\nS841    M    Q    R    A    R    P    D  ...    A    S    Q    V    A    P    A\nS849    M    H    I  NaN  NaN  NaN  NaN  ...  NaN    S    V    S    G    D    T\nS857    E    S    G  NaN  NaN  NaN  NaN  ...  NaN    Q    Q    T    T    A    A\nS860    E    S    G  NaN  NaN  NaN  NaN  ...  NaN    Q    Q    T    T    A    A\n\n[196 rows x 356 columns]", "y": "array([502. , 494. , 491. , 490. , 499. , 501. , 496. , 500. , 498. ,\n       500. , 502. , 488. , 491.5, 498. , 495.5, 500. , 497. , 494. ,\n       501. , 496. , 485. , 483. , 526. , 507. , 489. , 507. , 511. ,\n       488. , 501. , 488. , 494. , 499. , 524. , 494. , 490. , 492. ,\n       467. , 482. , 493. , 492. , 471. , 467. , 464. , 466. , 470. ,\n       471. , 554. , 544. , 499. , 500. , 500. , 498. , 356. , 358. ,\n       359. , 419. , 501. , 498. , 453. , 458. , 571. , 538. , 561. ,\n       561. , 546. , 552. , 502. , 514. , 512. , 500. , 506. , 359. ,\n       571. , 530. , 524. , 482. , 481. , 369. , 359. , 450. , 530. ,\n       527. , 528. , 519. , 476. , 438. , 503. , 439. , 497. , 434. ,\n       491. , 461. , 481. , 425. , 420. , 561. , 404. , 539. , 525. ,\n       505. , 420. , 452. , 516. , 517. , 491. , 508. , 510. , 508. ,\n       515. , 514. , 514. , 466. , 408. , 405. , 417. , 443. , 442. ,\n       487. , 467. , 476. , 488. , 423. , 507. , 511. , 484. , 360. ,\n       393. , 359. , 361. , 362. , 361. , 392. , 398. , 374. , 360. ,\n       366. , 360. , 389. , 422. , 360. , 361. , 404. , 404. , 418. ,\n       411. , 370. , 361. , 361. , 358. , 363. , 383. , 365. , 360. ,\n       414. , 363. , 359. , 359. , 359. , 403. , 367. , 359. , 360. ,\n       363. , 511. , 356. , 507. , 507. , 519. , 532. , 533. , 554. ,\n       553. , 532. , 501.7, 499. , 367. , 403. , 577. , 482. , 353. ,\n       485. , 539. , 532. , 532. , 558. , 559. , 534. , 532. , 439. ,\n       438. , 444. , 448. , 453. , 435. , 420. , 345. ])", "weight": "None", "message_clsname": "'Pipeline'", "message": "None", "**": "{}"}}