{"duration": 3.3886606693267822, "input_args": {"transformer": "Pipeline(steps=[('mc', MisCare(missing_threshold=0.05)), ('cc', ConstantCare()),\n                ('ur', URareCare(threshold=0.025)), ('cc2', ConstantCare()),\n                ('one_hot', CustomOneHotEncoder()),\n                ('feature_selection',\n                 FeatureSelection(alpha=0.1, model_type='reg')),\n                ('collinear_care',\n                 CollinearCare(dist_method='correlation', threshold=0.01))])", "X": "         p1   p2   p3 p4 p5 p6 p7 p8  ... p346 p347 p348 p349 p350 p351 p352 p353\nBovine    M    N    G  T  E  G  P  N  ...  NaN    T    S    Q    V    A    P    A\nS2      NaN  NaN  NaN  T  E  G  P  Y  ...  NaN  NaN    S    S    V    S    P    A\nS3      NaN  NaN  NaN  T  E  G  P  D  ...  NaN  NaN    S    S    V    S    P    A\nS4      NaN  NaN  NaN  T  E  G  P  F  ...  NaN  NaN    S    S    V    S    P    A\nS5      NaN  NaN  NaN  T  E  G  P  Y  ...  NaN  NaN    S    S    V    S    P    A\n...     ...  ...  ... .. .. .. .. ..  ...  ...  ...  ...  ...  ...  ...  ...  ...\nS356      M    N    G  T  E  G  P  N  ...  NaN    T    S    Q    V    A    P    A\nS359      M    N    G  T  E  G  E  N  ...    S    S    S    Q    V    S    P    A\nS360      M    N    G  T  E  G  P  N  ...    S    S    S    Q    V    S    P    A\nS361      M    N    G  T  E  G  P  N  ...    S    S    S    Q    V    S    P    A\nS362      M    N    G  T  E  G  P  N  ...    S    S    S    Q    V    S    P    A\n\n[328 rows x 353 columns]", "y": "array([500. , 502. , 481. , 494. , 494. , 491. , 486. , 490. , 490. ,\n       499. , 493. , 495. , 499. , 492. , 501. , 488. , 487. , 498. ,\n       502. , 500. , 497. , 504. , 496. , 500. , 498. , 505. , 500. ,\n       498. , 502. , 484. , 488. , 491. , 503. , 497.9, 491. , 497. ,\n       494. , 493. , 492. , 489. , 501. , 501. , 501. , 501. , 482. ,\n       502. , 501. , 502. , 496. , 485. , 486. , 486. , 485. , 496. ,\n       483. , 526. , 492. , 507. , 486. , 491. , 479. , 504. , 489. ,\n       524. , 467. , 452. , 496. , 467. , 476. , 488. , 505. , 536. ,\n       501. , 560.9, 463. , 359. , 355. , 425. , 356. , 358. , 360. ,\n       359. , 417. , 360. , 359. , 358. , 420. , 419. , 420. , 489. ,\n       488. , 482. , 501. , 496.5, 502. , 571. , 492. , 505. , 502. ,\n       502. , 500. , 506. , 502. , 502. , 503. , 506. , 503. , 505. ,\n       511. , 443. , 437. , 448. , 441. , 455. , 561. , 558. , 560. ,\n       571. , 532. , 553. , 509. , 545. , 531. , 516. , 532. , 435. ,\n       500. , 352. , 578. , 571. , 562. , 516. , 519. , 516. , 476. ,\n       438. , 408. , 353. , 503. , 358. , 497. , 492. , 508. , 505. ,\n       502. , 498. , 483. , 480. , 450. , 420. , 561. , 500. , 499. ,\n       404. , 450. , 486. , 479. , 539. , 502. , 525. , 496. , 435. ,\n       431. , 439. , 431. , 516. , 492. , 448. , 494. , 517. , 516. ,\n       491. , 460. , 519. , 462. , 517. , 493. , 416. , 452. , 466. ,\n       439. , 405. , 397. , 416. , 505. , 528. , 519. , 484. , 423. ,\n       368. , 507. , 508. , 503. , 488. , 491. , 491. , 489. , 505. ,\n       488. , 489. , 474. , 524. , 488. , 499. , 497. , 500. , 478. ,\n       361. , 360. , 359. , 360. , 360. , 393. , 359. , 393. , 552. ,\n       363. , 511. , 431. , 356. , 442. , 584. , 509. , 572. , 507. ,\n       563. , 563. , 561. , 558. , 558. , 536. , 561. , 564. , 532. ,\n       553. , 532. , 403. , 539. , 611. , 542. , 557. , 577. , 532. ,\n       532. , 537. , 518. , 482. , 431. , 485. , 494. , 490. , 551. ,\n       539. , 532. , 430. , 430. , 340. , 500. , 346. , 436. , 350. ,\n       513. , 357. , 364. , 359. , 360. , 371. , 355. , 423. , 360. ,\n       425. , 456. , 517. , 528. , 560. , 356. , 561. , 562. , 502. ,\n       369. , 488. , 550. , 497. , 361. , 363. , 533. , 535. , 486. ,\n       500. , 478. , 500. , 514. , 504. , 449. , 448. , 460. , 455. ,\n       457. , 500. , 480. , 498.7, 486.8, 481. , 474. , 430. , 499. ,\n       497. , 499. , 503. , 495. , 497. , 496. , 497. , 485. , 496. ,\n       496. , 496. , 487. , 494.5, 499. , 501. , 499. , 499. , 501. ,\n       501. , 501. , 501. , 499. ])", "weight": "None", "message_clsname": "'Pipeline'", "message": "None", "params": "{'fit': {}, 'partial_fit': {}, 'predict': {}, 'predict_proba': {}, 'predict_log_proba': {}, 'decision_function': {}, 'score': {}, 'split': {}, 'transform': {}, 'inverse_transform': {}, 'fit_transform': {}, 'fit_predict': {}}"}, "time": 1730404549.4182892}